LICENSE.txt
MANIFEST.in
README.rst
requirements-test.txt
requirements.txt
setup.py
pycabara/Element.py
pycabara/Selenium.py
pycabara/Session.py
pycabara/__init__.py
pycabara/info.py
pycabara.egg-info/PKG-INFO
pycabara.egg-info/SOURCES.txt
pycabara.egg-info/dependency_links.txt
pycabara.egg-info/not-zip-safe
pycabara.egg-info/requires.txt
pycabara.egg-info/top_level.txt