Metadata-Version: 1.1
Name: pycabara
Version: 0.4
Summary: Python implementation of Capybara, an acceptance test framework for web applications
Home-page: http://github.com/ruthlesshelp/pycabara
Author: Stephen Ritchie
Author-email: ruthlesshelp@gmail.com
License: MIT
Keywords: acceptance test Capybara bdd
Platform: UNKNOWN
Classifier: Development Status :: 1 - Planning
Classifier: License :: OSI Approved :: MIT License
Classifier: Programming Language :: Python :: 2.7
Classifier: Topic :: Software Development :: Testing
